{"success":true,"message":"Todos os 16 ativos foram atualizados com sucesso!","updated_count":16,"failed_count":0,"updated_assets":[{"ticker":"VGIA11","old_price":10.1,"new_price":10.1,"change":1.101},{"ticker":"BTHF11","old_price":8.83,"new_price":8.83,"change":-0.451},{"ticker":"ITSA4","old_price":12.06,"new_price":12.06,"change":-0.413},{"ticker":"BTLG11","old_price":103.18,"new_price":103.18,"change":0.029},{"ticker":"CMIG4","old_price":10.94,"new_price":10.94,"change":-0.182},{"ticker":"PETR4","old_price":30.49,"new_price":30.49,"change":0.627},{"ticker":"SAPR4","old_price":8.46,"new_price":8.46,"change":0.955},{"ticker":"XPML11","old_price":109.81,"new_price":109.81,"change":-0.155},{"ticker":"BBAS3","old_price":21.85,"new_price":21.85,"change":-0.046},{"ticker":"CPTR11","old_price":8.38,"new_price":8.38,"change":-0.23800000000000002},{"ticker":"MXRF11","old_price":9.5,"new_price":9.5,"change":-0.105},{"ticker":"BBSE3","old_price":34.68,"new_price":34.68,"change":-0.886},{"ticker":"TAEE4","old_price":13.47,"new_price":13.47,"change":0.074},{"ticker":"ABCB4","old_price":23.89,"new_price":23.89,"change":-0.084},{"ticker":"VALE3","old_price":75.11,"new_price":75.11,"change":0.522},{"ticker":"ARRI11","old_price":6.6,"new_price":6.6,"change":0}],"failed_assets":[]}